notion_util/__init__.py
notion_util/client.py
notion_util/extractors.py
notion_util/markdown.py
notion_util/text_utils.py
notion_util/util.py
notion_util-1.2.1.dist-info/METADATA
notion_util-1.2.1.dist-info/WHEEL
notion_util-1.2.1.dist-info/top_level.txt
notion_util-1.2.1.dist-info/RECORD
