Metadata-Version: 2.1
Name: notion-util
Version: 1.2.1
Summary: Unofficial Python API client for Notion.so
Home-page: https://github.com/tatsu-i/notion-util
Author: tatsuiman
Classifier: Programming Language :: Python :: 3
Classifier: License :: OSI Approved :: MIT License
Classifier: Operating System :: OS Independent
Requires-Python: >=3.5
Requires-Dist: requests
